MANIFEST.in
VERSION
requirements.txt
setup.py
drf_toolbox/.VERSION
drf_toolbox/__init__.py
drf_toolbox/compat.py
drf_toolbox/decorators.py
drf_toolbox/routers.py
drf_toolbox/viewsets.py
drf_toolbox.egg-info/PKG-INFO
drf_toolbox.egg-info/SOURCES.txt
drf_toolbox.egg-info/dependency_links.txt
drf_toolbox.egg-info/not-zip-safe
drf_toolbox.egg-info/requires.txt
drf_toolbox.egg-info/top_level.txt
drf_toolbox/renderers/__init__.py
drf_toolbox/renderers/api.py
drf_toolbox/renderers/json.py
drf_toolbox/serializers/__init__.py
drf_toolbox/serializers/base.py
drf_toolbox/serializers/widgets.py
drf_toolbox/serializers/fields/__init__.py
drf_toolbox/serializers/fields/api.py
drf_toolbox/serializers/fields/postgres.py
drf_toolbox/serializers/fields/related.py
drf_toolbox/utils/__init__.py
drf_toolbox/utils/json.py