Metadata-Version: 1.1
Name: drf-toolbox
Version: 0.1.4
Summary: A collection of useful functionality on top of Django REST Framework.
Home-page: https://github.com/feedmagnet/drf-toolbox
Author: FeedMagnet
Author-email: tech@feedmagnet.com
License: New BSD
Platform: UNKNOWN
Classifier: Development Status :: 5 - Production/Stable
Classifier: Intended Audience :: Developers
Classifier: Operating System :: OS Independent
Classifier: Programming Language :: Python
Classifier: Programming Language :: Python :: 2.7
Classifier: Programming Language :: Python :: 3.3
Classifier: Topic :: Software Development
Provides: drf_toolbox
